scrapy_redis_cf/__init__.py
scrapy_redis_cf/defaults.py
scrapy_redis_cf/dupefilter.py
scrapy_redis_cf/exception.py
scrapy_redis_cf/scheduler.py
scrapy_redis_cf-0.0.1.dist-info/METADATA
scrapy_redis_cf-0.0.1.dist-info/WHEEL
scrapy_redis_cf-0.0.1.dist-info/licenses/LICENSE
scrapy_redis_cf-0.0.1.dist-info/RECORD
