Metadata-Version: 2.1
Name: scrapy-redis-cf
Version: 0.0.1
Summary: scrapy_redis use cuckoofilter
Project-URL: Homepage, https://github.com/kanadeblisst/scrapy_redis_cf
Project-URL: Bug Tracker, https://github.com/kanadeblisst/scrapy_redis_cf/issues
Author-email: kanade <kanade@blisst.cn>
License: Copyright (c) 2018 The Python Packaging Authority
License-File: LICENSE
Classifier: License :: OSI Approved :: MIT License
Classifier: Operating System :: OS Independent
Classifier: Programming Language :: Python :: 3
Requires-Python: >=3.7
Requires-Dist: scrapy-redis>=0.6.8
